llm_telemetry_toolkit/__init__.py
llm_telemetry_toolkit/py.typed
llm_telemetry_toolkit/core/__init__.py
llm_telemetry_toolkit/core/context.py
llm_telemetry_toolkit/core/decorators.py
llm_telemetry_toolkit/core/logger.py
llm_telemetry_toolkit/interface/__init__.py
llm_telemetry_toolkit/interface/cli.py
llm_telemetry_toolkit/io/__init__.py
llm_telemetry_toolkit/io/formatters.py
llm_telemetry_toolkit/io/parser.py
llm_telemetry_toolkit/io/utils.py
llm_telemetry_toolkit/models/__init__.py
llm_telemetry_toolkit/models/config.py
llm_telemetry_toolkit/models/results.py
llm_telemetry_toolkit/models/schema.py
llm_telemetry_toolkit-0.1.0.dist-info/METADATA
llm_telemetry_toolkit-0.1.0.dist-info/WHEEL
llm_telemetry_toolkit-0.1.0.dist-info/RECORD
