Metadata-Version: 2.4
Name: llm-telemetry-toolkit
Version: 0.1.0
Summary: A standardized, file-based telemetry toolkit for LLM Agents.
Project-URL: Homepage, https://github.com/imyourboyroy/llm-telemetry-toolkit
Project-URL: Repository, https://github.com/imyourboyroy/llm-telemetry-toolkit
Project-URL: Bug Tracker, https://github.com/imyourboyroy/llm-telemetry-toolkit/issues
Author-email: Roy Dawson IV <roy.dawson.iv@gmail.com>
License-Expression: MIT
Keywords: agent,json,llm,logging,markdown,observability,pydantic,telemetry
Classifier: Development Status :: 4 - Beta
Classifier: License :: OSI Approved :: MIT License
Classifier: Operating System :: OS Independent
Classifier: Programming Language :: Python :: 3
Classifier: Programming Language :: Python :: 3.8
Classifier: Programming Language :: Python :: 3.9
Classifier: Programming Language :: Python :: 3.10
Classifier: Programming Language :: Python :: 3.11
Classifier: Programming Language :: Python :: 3.12
Classifier: Programming Language :: Python :: 3.13
Classifier: Topic :: Scientific/Engineering :: Artificial Intelligence
Classifier: Topic :: Software Development :: Libraries :: Python Modules
Classifier: Topic :: System :: Logging
Classifier: Typing :: Typed
Requires-Python: >=3.8
Requires-Dist: pydantic>=2.0
Requires-Dist: rich>=10.0
